tinerator/__init__.py
tinerator/_version.py
tinerator/constants.py
tinerator/logging.py
tinerator/examples/__init__.py
tinerator/examples/data/README.md
tinerator/examples/data/Borden/dem0.5m.dat
tinerator/examples/data/Borden/dem1m.dat
tinerator/examples/data/new_mexico/README.md
tinerator/examples/data/new_mexico/rasters/USGS_NED_13_n37w108_Clipped.tif
tinerator/examples/data/new_mexico/rasters/USGS_NED_13_n37w108_Clipped.tif.aux.xml
tinerator/examples/data/new_mexico/shapefiles/NHDFlowline/NHDFlowline.cpg
tinerator/examples/data/new_mexico/shapefiles/NHDFlowline/NHDFlowline.dbf
tinerator/examples/data/new_mexico/shapefiles/NHDFlowline/NHDFlowline.prj
tinerator/examples/data/new_mexico/shapefiles/NHDFlowline/NHDFlowline.qpj
tinerator/examples/data/new_mexico/shapefiles/NHDFlowline/NHDFlowline.shp
tinerator/examples/data/new_mexico/shapefiles/NHDFlowline/NHDFlowline.shx
tinerator/examples/data/new_mexico/shapefiles/WBDHU12/WBDHU12.cpg
tinerator/examples/data/new_mexico/shapefiles/WBDHU12/WBDHU12.dbf
tinerator/examples/data/new_mexico/shapefiles/WBDHU12/WBDHU12.prj
tinerator/examples/data/new_mexico/shapefiles/WBDHU12/WBDHU12.qpj
tinerator/examples/data/new_mexico/shapefiles/WBDHU12/WBDHU12.shp
tinerator/examples/data/new_mexico/shapefiles/WBDHU12/WBDHU12.shx
tinerator/gis/__init__.py
tinerator/gis/distance_maps.py
tinerator/gis/geometry.py
tinerator/gis/geoutils.py
tinerator/gis/gis_tools.py
tinerator/gis/gis_triangulation.py
tinerator/gis/raster.py
tinerator/gis/raster_boundary.py
tinerator/gis/vector.py
tinerator/gis/watershed_delin.py
tinerator/meshing/__init__.py
tinerator/meshing/adjacency.py
tinerator/meshing/extrude_mesh.py
tinerator/meshing/hillslope_mesh.py
tinerator/meshing/lagrit_helper.py
tinerator/meshing/layering.py
tinerator/meshing/map_elevation_to_surface.py
tinerator/meshing/mesh.py
tinerator/meshing/mesh_attributes.py
tinerator/meshing/mesh_metrics.py
tinerator/meshing/meshing_types.py
tinerator/meshing/meshing_utils.py
tinerator-0.9.1.dist-info/LICENSE
tinerator-0.9.1.dist-info/METADATA
tinerator-0.9.1.dist-info/WHEEL
tinerator-0.9.1.dist-info/top_level.txt
tinerator-0.9.1.dist-info/RECORD
