Metadata-Version: 2.1
Name: tinerator
Version: 0.9.1
Summary: "Intuitive and powerful unstructured geospatial mesh generation from GIS data."
Home-page: https://github.com/lanl/tinerator
Author: Daniel Livingston, Los Alamos National Laboratory
Author-email: daniel.livingston@live.com
License: UNKNOWN
Platform: UNKNOWN
Classifier: Development Status :: 5 - Production/Stable
Classifier: Operating System :: OS Independent
Classifier: Operating System :: MacOS
Classifier: Operating System :: Unix
Classifier: Operating System :: POSIX
Classifier: Operating System :: Microsoft :: Windows
Classifier: Programming Language :: Python :: 3
Classifier: Programming Language :: Python :: 3 :: Only
Classifier: Intended Audience :: Science/Research
Classifier: Topic :: Software Development :: Libraries
Classifier: Topic :: Software Development :: Libraries :: Python Modules
Classifier: Topic :: Scientific/Engineering :: GIS
Classifier: Topic :: Scientific/Engineering :: Hydrology
Classifier: Topic :: Scientific/Engineering :: Visualization
Requires-Python: >=3.6
License-File: LICENSE
Requires-Dist: setuptools (>=46.1.0)
Requires-Dist: setuptools-scm (>=5)
Requires-Dist: tomlkit (<2,>=0.7.0)
Requires-Dist: packaging (>=20.7)
Requires-Dist: numpy (>=1.19.0)
Requires-Dist: scipy (>=1.0)
Requires-Dist: Fiona (>=1.0)
Requires-Dist: pyproj (>=3.0)
Requires-Dist: Shapely (>=1.0)
Requires-Dist: snowy (>=0.0.9)
Requires-Dist: pyshp (>=2)
Requires-Dist: vtk (<10,>=9)
Requires-Dist: pyvista (>=0.30)
Requires-Dist: meshio (>=4.0.0)
Requires-Dist: MeshPy (>=2020.0)
Requires-Dist: plotly (>=5.0)
Requires-Dist: rich (>=10.0)
Requires-Dist: importlib-metadata ; python_version < "3.8"
